ez_setup.py
setup.cfg
setup.py
loadimpact/__init__.py
loadimpact/clients.py
loadimpact/exceptions.py
loadimpact/fields.py
loadimpact/resources.py
loadimpact/utils.py
loadimpact/version.py
loadimpact.egg-info/PKG-INFO
loadimpact.egg-info/SOURCES.txt
loadimpact.egg-info/dependency_links.txt
loadimpact.egg-info/requires.txt
loadimpact.egg-info/top_level.txt
test/test_clients.py
test/test_fields.py
test/test_resources.py
test/test_utils.py