Metadata-Version: 1.1
Name: loadimpact
Version: 1.1.3
Summary: The Load Impact SDK provides access to Load Impact's cloud-based performance testing platform
Home-page: http://developers.loadimpact.com/
Author: Load Impact
Author-email: support@loadimpact.com
License: LICENSE.txt
Keywords: loadimpact api rest sdk
Platform: UNKNOWN
Classifier: Intended Audience :: Developers
Classifier: Natural Language :: English
Classifier: Operating System :: OS Independent
Classifier: Programming Language :: Python
Classifier: Programming Language :: Python :: 2
Classifier: Programming Language :: Python :: 3
Classifier: Topic :: Software Development :: Libraries :: Python Modules
